{
    "name": "Igora Drive",
    "short_name": "IgoraK CW",
    "start_finish": {
        "lat": 605160325,
        "lon": 301891501,
        "elev": 212000
    },
    "pts": [
        {
            "lat": 605160325,
            "lon": 301891501,
            "elev": 212000
        },
        {
            "lat": 605162995,
            "lon": 301887993,
            "elev": 212000
        },
        {
            "lat": 605163725,
            "lon": 301887207,
            "elev": 212000
        },
        {
            "lat": 605164691,
            "lon": 301886328,
            "elev": 212000
        },
        {
            "lat": 605165397,
            "lon": 301885817,
            "elev": 212000
        },
        {
            "lat": 605166100,
            "lon": 301885475,
            "elev": 212000
        },
        {
            "lat": 605167307,
            "lon": 301885177,
            "elev": 212000
        },
        {
            "lat": 605167983,
            "lon": 301885231,
            "elev": 212000
        },
        {
            "lat": 605168655,
            "lon": 301885422,
            "elev": 212000
        },
        {
            "lat": 605169505,
            "lon": 301885907,
            "elev": 212000
        },
        {
            "lat": 605170115,
            "lon": 301886428,
            "elev": 212000
        },
        {
            "lat": 605170711,
            "lon": 301887062,
            "elev": 212000
        },
        {
            "lat": 605171476,
            "lon": 301888080,
            "elev": 212000
        },
        {
            "lat": 605172013,
            "lon": 301888974,
            "elev": 212000
        },
        {
            "lat": 605172503,
            "lon": 301889979,
            "elev": 212000
        },
        {
            "lat": 605173078,
            "lon": 301891476,
            "elev": 212000
        },
        {
            "lat": 605173470,
            "lon": 301892636,
            "elev": 212000
        },
        {
            "lat": 605173826,
            "lon": 301893988,
            "elev": 212000
        },
        {
            "lat": 605174047,
            "lon": 301895515,
            "elev": 212000
        },
        {
            "lat": 605174167,
            "lon": 301896787,
            "elev": 212000
        },
        {
            "lat": 605174227,
            "lon": 301898084,
            "elev": 212000
        },
        {
            "lat": 605174266,
            "lon": 301900517,
            "elev": 212000
        },
        {
            "lat": 605174242,
            "lon": 301900996,
            "elev": 212000
        },
        {
            "lat": 605174192,
            "lon": 301901425,
            "elev": 212000
        },
        {
            "lat": 605174088,
            "lon": 301901987,
            "elev": 212000
        },
        {
            "lat": 605173950,
            "lon": 301902512,
            "elev": 212000
        },
        {
            "lat": 605173818,
            "lon": 301902862,
            "elev": 212000
        },
        {
            "lat": 605173667,
            "lon": 301903161,
            "elev": 212000
        },
        {
            "lat": 605173497,
            "lon": 301903433,
            "elev": 212000
        },
        {
            "lat": 605173304,
            "lon": 301903666,
            "elev": 212000
        },
        {
            "lat": 605173031,
            "lon": 301903891,
            "elev": 212000
        },
        {
            "lat": 605172745,
            "lon": 301904049,
            "elev": 212000
        },
        {
            "lat": 605172510,
            "lon": 301904106,
            "elev": 212000
        },
        {
            "lat": 605172279,
            "lon": 301904118,
            "elev": 212000
        },
        {
            "lat": 605171822,
            "lon": 301904089,
            "elev": 212000
        },
        {
            "lat": 605171280,
            "lon": 301904133,
            "elev": 212000
        },
        {
            "lat": 605171097,
            "lon": 301904215,
            "elev": 212000
        },
        {
            "lat": 605170924,
            "lon": 301904344,
            "elev": 212000
        },
        {
            "lat": 605170727,
            "lon": 301904550,
            "elev": 212000
        },
        {
            "lat": 605170528,
            "lon": 301904844,
            "elev": 212000
        },
        {
            "lat": 605170343,
            "lon": 301905291,
            "elev": 212000
        },
        {
            "lat": 605170156,
            "lon": 301905830,
            "elev": 212000
        },
        {
            "lat": 605169955,
            "lon": 301906260,
            "elev": 212000
        },
        {
            "lat": 605169776,
            "lon": 301906466,
            "elev": 212000
        },
        {
            "lat": 605169588,
            "lon": 301906600,
            "elev": 212000
        },
        {
            "lat": 605169409,
            "lon": 301906682,
            "elev": 212000
        },
        {
            "lat": 605169214,
            "lon": 301906710,
            "elev": 212000
        },
        {
            "lat": 605169025,
            "lon": 301906679,
            "elev": 212000
        },
        {
            "lat": 605168829,
            "lon": 301906617,
            "elev": 212000
        },
        {
            "lat": 605168627,
            "lon": 301906509,
            "elev": 212000
        },
        {
            "lat": 605168353,
            "lon": 301906304,
            "elev": 212000
        },
        {
            "lat": 605168091,
            "lon": 301905965,
            "elev": 212000
        },
        {
            "lat": 605167892,
            "lon": 301905655,
            "elev": 212000
        },
        {
            "lat": 605167588,
            "lon": 301905145,
            "elev": 212000
        },
        {
            "lat": 605167297,
            "lon": 301904598,
            "elev": 212000
        },
        {
            "lat": 605164902,
            "lon": 301899603,
            "elev": 210000
        },
        {
            "lat": 605164683,
            "lon": 301899190,
            "elev": 210000
        },
        {
            "lat": 605164483,
            "lon": 301898906,
            "elev": 210000
        },
        {
            "lat": 605164167,
            "lon": 301898634,
            "elev": 210000
        },
        {
            "lat": 605163832,
            "lon": 301898464,
            "elev": 210000
        },
        {
            "lat": 605163549,
            "lon": 301898420,
            "elev": 210000
        },
        {
            "lat": 605163272,
            "lon": 301898454,
            "elev": 210000
        },
        {
            "lat": 605163002,
            "lon": 301898549,
            "elev": 210000
        },
        {
            "lat": 605162732,
            "lon": 301898704,
            "elev": 210000
        },
        {
            "lat": 605162415,
            "lon": 301898941,
            "elev": 210000
        },
        {
            "lat": 605162112,
            "lon": 301899228,
            "elev": 210000
        },
        {
            "lat": 605161889,
            "lon": 301899493,
            "elev": 210000
        },
        {
            "lat": 605161688,
            "lon": 301899793,
            "elev": 210000
        },
        {
            "lat": 605161507,
            "lon": 301900136,
            "elev": 210000
        },
        {
            "lat": 605161339,
            "lon": 301900530,
            "elev": 210000
        },
        {
            "lat": 605160962,
            "lon": 301901695,
            "elev": 210000
        },
        {
            "lat": 605160490,
            "lon": 301903633,
            "elev": 210000
        },
        {
            "lat": 605160119,
            "lon": 301904833,
            "elev": 210000
        },
        {
            "lat": 605159954,
            "lon": 301905231,
            "elev": 210000
        },
        {
            "lat": 605159779,
            "lon": 301905578,
            "elev": 210000
        },
        {
            "lat": 605159590,
            "lon": 301905890,
            "elev": 210000
        },
        {
            "lat": 605159380,
            "lon": 301906164,
            "elev": 210000
        },
        {
            "lat": 605159093,
            "lon": 301906437,
            "elev": 210000
        },
        {
            "lat": 605158793,
            "lon": 301906644,
            "elev": 210000
        },
        {
            "lat": 605158554,
            "lon": 301906744,
            "elev": 210000
        },
        {
            "lat": 605158320,
            "lon": 301906786,
            "elev": 210000
        },
        {
            "lat": 605158099,
            "lon": 301906790,
            "elev": 210000
        },
        {
            "lat": 605157876,
            "lon": 301906733,
            "elev": 210000
        },
        {
            "lat": 605157602,
            "lon": 301906560,
            "elev": 210000
        },
        {
            "lat": 605157344,
            "lon": 301906315,
            "elev": 210000
        },
        {
            "lat": 605157169,
            "lon": 301906078,
            "elev": 210000
        },
        {
            "lat": 605157018,
            "lon": 301905803,
            "elev": 210000
        },
        {
            "lat": 605156883,
            "lon": 301905489,
            "elev": 210000
        },
        {
            "lat": 605156768,
            "lon": 301905124,
            "elev": 210000
        },
        {
            "lat": 605156652,
            "lon": 301904581,
            "elev": 210000
        },
        {
            "lat": 605156573,
            "lon": 301904005,
            "elev": 210000
        },
        {
            "lat": 605156548,
            "lon": 301903545,
            "elev": 210000
        },
        {
            "lat": 605156553,
            "lon": 301903094,
            "elev": 210000
        },
        {
            "lat": 605156582,
            "lon": 301902637,
            "elev": 210000
        },
        {
            "lat": 605156642,
            "lon": 301902170,
            "elev": 210000
        },
        {
            "lat": 605156767,
            "lon": 301901562,
            "elev": 210000
        },
        {
            "lat": 605156927,
            "lon": 301900977,
            "elev": 210000
        },
        {
            "lat": 605157085,
            "lon": 301900546,
            "elev": 210000
        },
        {
            "lat": 605157261,
            "lon": 301900159,
            "elev": 210000
        },
        {
            "lat": 605157671,
            "lon": 301899441,
            "elev": 210000
        },
        {
            "lat": 605162131,
            "lon": 301893254,
            "elev": 212000
        },
        {
            "lat": 605163217,
            "lon": 301891908,
            "elev": 212000
        },
        {
            "lat": 605163924,
            "lon": 301891288,
            "elev": 212000
        },
        {
            "lat": 605164185,
            "lon": 301891141,
            "elev": 212000
        },
        {
            "lat": 605164439,
            "lon": 301891060,
            "elev": 212000
        },
        {
            "lat": 605164685,
            "lon": 301891045,
            "elev": 212000
        },
        {
            "lat": 605164957,
            "lon": 301891096,
            "elev": 212000
        },
        {
            "lat": 605166142,
            "lon": 301891660,
            "elev": 212000
        },
        {
            "lat": 605166671,
            "lon": 301891803,
            "elev": 212000
        },
        {
            "lat": 605167379,
            "lon": 301891822,
            "elev": 212000
        },
        {
            "lat": 605167905,
            "lon": 301891676,
            "elev": 212000
        },
        {
            "lat": 605169143,
            "lon": 301891238,
            "elev": 212000
        },
        {
            "lat": 605169434,
            "lon": 301891198,
            "elev": 212000
        },
        {
            "lat": 605169894,
            "lon": 301891283,
            "elev": 212000
        },
        {
            "lat": 605170186,
            "lon": 301891426,
            "elev": 212000
        },
        {
            "lat": 605170515,
            "lon": 301891685,
            "elev": 212000
        },
        {
            "lat": 605170825,
            "lon": 301892089,
            "elev": 212000
        },
        {
            "lat": 605171281,
            "lon": 301892906,
            "elev": 212000
        },
        {
            "lat": 605171672,
            "lon": 301893710,
            "elev": 212000
        },
        {
            "lat": 605172085,
            "lon": 301894824,
            "elev": 212000
        },
        {
            "lat": 605172207,
            "lon": 301895250,
            "elev": 212000
        },
        {
            "lat": 605172303,
            "lon": 301895673,
            "elev": 212000
        },
        {
            "lat": 605172377,
            "lon": 301896099,
            "elev": 212000
        },
        {
            "lat": 605172423,
            "lon": 301896549,
            "elev": 212000
        },
        {
            "lat": 605172432,
            "lon": 301897130,
            "elev": 212000
        },
        {
            "lat": 605172404,
            "lon": 301897701,
            "elev": 212000
        },
        {
            "lat": 605172361,
            "lon": 301898101,
            "elev": 212000
        },
        {
            "lat": 605172287,
            "lon": 301898470,
            "elev": 212000
        },
        {
            "lat": 605172204,
            "lon": 301898747,
            "elev": 212000
        },
        {
            "lat": 605172100,
            "lon": 301899013,
            "elev": 212000
        },
        {
            "lat": 605171981,
            "lon": 301899240,
            "elev": 212000
        },
        {
            "lat": 605171846,
            "lon": 301899420,
            "elev": 212000
        },
        {
            "lat": 605171696,
            "lon": 301899559,
            "elev": 212000
        },
        {
            "lat": 605171541,
            "lon": 301899649,
            "elev": 212000
        },
        {
            "lat": 605171377,
            "lon": 301899680,
            "elev": 212000
        },
        {
            "lat": 605171208,
            "lon": 301899661,
            "elev": 212000
        },
        {
            "lat": 605171050,
            "lon": 301899606,
            "elev": 212000
        },
        {
            "lat": 605170867,
            "lon": 301899484,
            "elev": 212000
        },
        {
            "lat": 605170700,
            "lon": 301899306,
            "elev": 212000
        },
        {
            "lat": 605170547,
            "lon": 301899088,
            "elev": 212000
        },
        {
            "lat": 605170397,
            "lon": 301898801,
            "elev": 212000
        },
        {
            "lat": 605170145,
            "lon": 301898126,
            "elev": 212000
        },
        {
            "lat": 605169885,
            "lon": 301897402,
            "elev": 212000
        },
        {
            "lat": 605169735,
            "lon": 301897028,
            "elev": 212000
        },
        {
            "lat": 605169536,
            "lon": 301896599,
            "elev": 212000
        },
        {
            "lat": 605169345,
            "lon": 301896283,
            "elev": 212000
        },
        {
            "lat": 605169155,
            "lon": 301896065,
            "elev": 212000
        },
        {
            "lat": 605168934,
            "lon": 301895860,
            "elev": 212000
        },
        {
            "lat": 605168708,
            "lon": 301895738,
            "elev": 212000
        },
        {
            "lat": 605168455,
            "lon": 301895721,
            "elev": 212000
        },
        {
            "lat": 605168160,
            "lon": 301895799,
            "elev": 212000
        },
        {
            "lat": 605167871,
            "lon": 301895958,
            "elev": 212000
        },
        {
            "lat": 605167568,
            "lon": 301896207,
            "elev": 212000
        },
        {
            "lat": 605167274,
            "lon": 301896509,
            "elev": 212000
        },
        {
            "lat": 605166636,
            "lon": 301897378,
            "elev": 210000
        },
        {
            "lat": 605166199,
            "lon": 301898109,
            "elev": 210000
        },
        {
            "lat": 605165814,
            "lon": 301898908,
            "elev": 210000
        },
        {
            "lat": 605162976,
            "lon": 301905046,
            "elev": 210000
        },
        {
            "lat": 605162312,
            "lon": 301906482,
            "elev": 210000
        },
        {
            "lat": 605161772,
            "lon": 301907506,
            "elev": 210000
        },
        {
            "lat": 605161206,
            "lon": 301908437,
            "elev": 210000
        },
        {
            "lat": 605160399,
            "lon": 301909454,
            "elev": 210000
        },
        {
            "lat": 605159760,
            "lon": 301910007,
            "elev": 210000
        },
        {
            "lat": 605159088,
            "lon": 301910399,
            "elev": 210000
        },
        {
            "lat": 605158158,
            "lon": 301910753,
            "elev": 210000
        },
        {
            "lat": 605157442,
            "lon": 301910919,
            "elev": 210000
        },
        {
            "lat": 605156709,
            "lon": 301911013,
            "elev": 210000
        },
        {
            "lat": 605154479,
            "lon": 301910958,
            "elev": 210000
        },
        {
            "lat": 605152714,
            "lon": 301910670,
            "elev": 210000
        },
        {
            "lat": 605152389,
            "lon": 301910523,
            "elev": 210000
        },
        {
            "lat": 605152124,
            "lon": 301910335,
            "elev": 210000
        },
        {
            "lat": 605151919,
            "lon": 301910129,
            "elev": 210000
        },
        {
            "lat": 605151736,
            "lon": 301909886,
            "elev": 210000
        },
        {
            "lat": 605151575,
            "lon": 301909625,
            "elev": 210000
        },
        {
            "lat": 605151433,
            "lon": 301909320,
            "elev": 210000
        },
        {
            "lat": 605151341,
            "lon": 301909056,
            "elev": 210000
        },
        {
            "lat": 605151260,
            "lon": 301908762,
            "elev": 210000
        },
        {
            "lat": 605151201,
            "lon": 301908459,
            "elev": 210000
        },
        {
            "lat": 605151170,
            "lon": 301908158,
            "elev": 210000
        },
        {
            "lat": 605151160,
            "lon": 301907848,
            "elev": 210000
        },
        {
            "lat": 605151168,
            "lon": 301907537,
            "elev": 210000
        },
        {
            "lat": 605151218,
            "lon": 301907046,
            "elev": 210000
        },
        {
            "lat": 605151300,
            "lon": 301906576,
            "elev": 210000
        },
        {
            "lat": 605151381,
            "lon": 301906222,
            "elev": 210000
        },
        {
            "lat": 605151499,
            "lon": 301905848,
            "elev": 210000
        },
        {
            "lat": 605152463,
            "lon": 301903690,
            "elev": 210000
        },
        {
            "lat": 605154476,
            "lon": 301900044,
            "elev": 210000
        },
        {
            "lat": 605157015,
            "lon": 301896174,
            "elev": 210000
        },
        {
            "lat": 605160150,
            "lon": 301891731,
            "elev": 212000
        },
        {
            "lat": 605160325,
            "lon": 301891501,
            "elev": 212000
        }
    ]
}