{
    "name": "Piedmont Kartway",
    "short_name": "PiedmontK",
    "start_finish": {
        "lat": 352914618,
        "lon": -817416249,
        "elev": 0
    },
    "pts": [
        {
            "lat": 352914618,
            "lon": -817416249,
            "elev": 0
        },
        {
            "lat": 352914653,
            "lon": -817416845,
            "elev": 273000
        },
        {
            "lat": 352914630,
            "lon": -817418842,
            "elev": 273000
        },
        {
            "lat": 352914486,
            "lon": -817419840,
            "elev": 273000
        },
        {
            "lat": 352914302,
            "lon": -817420691,
            "elev": 273000
        },
        {
            "lat": 352914216,
            "lon": -817420983,
            "elev": 273000
        },
        {
            "lat": 352914108,
            "lon": -817421252,
            "elev": 273000
        },
        {
            "lat": 352913849,
            "lon": -817421799,
            "elev": 274000
        },
        {
            "lat": 352913551,
            "lon": -817422328,
            "elev": 276000
        },
        {
            "lat": 352913364,
            "lon": -817422586,
            "elev": 276000
        },
        {
            "lat": 352913171,
            "lon": -817422806,
            "elev": 276000
        },
        {
            "lat": 352912727,
            "lon": -817423218,
            "elev": 276000
        },
        {
            "lat": 352912223,
            "lon": -817423549,
            "elev": 276000
        },
        {
            "lat": 352911675,
            "lon": -817423798,
            "elev": 276000
        },
        {
            "lat": 352911094,
            "lon": -817423944,
            "elev": 275000
        },
        {
            "lat": 352910793,
            "lon": -817423973,
            "elev": 275000
        },
        {
            "lat": 352910491,
            "lon": -817423970,
            "elev": 275000
        },
        {
            "lat": 352910186,
            "lon": -817423931,
            "elev": 275000
        },
        {
            "lat": 352909886,
            "lon": -817423858,
            "elev": 275000
        },
        {
            "lat": 352909589,
            "lon": -817423747,
            "elev": 275000
        },
        {
            "lat": 352909302,
            "lon": -817423604,
            "elev": 275000
        },
        {
            "lat": 352909021,
            "lon": -817423428,
            "elev": 275000
        },
        {
            "lat": 352908754,
            "lon": -817423223,
            "elev": 275000
        },
        {
            "lat": 352908498,
            "lon": -817422987,
            "elev": 275000
        },
        {
            "lat": 352908262,
            "lon": -817422725,
            "elev": 274000
        },
        {
            "lat": 352908044,
            "lon": -817422431,
            "elev": 274000
        },
        {
            "lat": 352907849,
            "lon": -817422116,
            "elev": 273000
        },
        {
            "lat": 352907520,
            "lon": -817421420,
            "elev": 273000
        },
        {
            "lat": 352907269,
            "lon": -817420668,
            "elev": 273000
        },
        {
            "lat": 352906957,
            "lon": -817419052,
            "elev": 273000
        },
        {
            "lat": 352906847,
            "lon": -817417365,
            "elev": 273000
        },
        {
            "lat": 352906843,
            "lon": -817415595,
            "elev": 273000
        },
        {
            "lat": 352907086,
            "lon": -817413214,
            "elev": 274000
        },
        {
            "lat": 352907217,
            "lon": -817412626,
            "elev": 274000
        },
        {
            "lat": 352907622,
            "lon": -817411514,
            "elev": 274000
        },
        {
            "lat": 352907752,
            "lon": -817411257,
            "elev": 274000
        },
        {
            "lat": 352907905,
            "lon": -817411015,
            "elev": 274000
        },
        {
            "lat": 352908244,
            "lon": -817410568,
            "elev": 274000
        },
        {
            "lat": 352908612,
            "lon": -817410152,
            "elev": 275000
        },
        {
            "lat": 352909029,
            "lon": -817409811,
            "elev": 275000
        },
        {
            "lat": 352909475,
            "lon": -817409541,
            "elev": 275000
        },
        {
            "lat": 352909943,
            "lon": -817409358,
            "elev": 275000
        },
        {
            "lat": 352910421,
            "lon": -817409261,
            "elev": 275000
        },
        {
            "lat": 352910903,
            "lon": -817409252,
            "elev": 275000
        },
        {
            "lat": 352911373,
            "lon": -817409334,
            "elev": 274000
        },
        {
            "lat": 352911824,
            "lon": -817409500,
            "elev": 274000
        },
        {
            "lat": 352912249,
            "lon": -817409740,
            "elev": 274000
        },
        {
            "lat": 352912640,
            "lon": -817410051,
            "elev": 274000
        },
        {
            "lat": 352912996,
            "lon": -817410427,
            "elev": 274000
        },
        {
            "lat": 352913596,
            "lon": -817411322,
            "elev": 273000
        },
        {
            "lat": 352913725,
            "lon": -817411556,
            "elev": 273000
        },
        {
            "lat": 352913838,
            "lon": -817411824,
            "elev": 273000
        },
        {
            "lat": 352914160,
            "lon": -817412867,
            "elev": 272000
        },
        {
            "lat": 352914447,
            "lon": -817414074,
            "elev": 272000
        },
        {
            "lat": 352914623,
            "lon": -817415712,
            "elev": 272000
        },
        {
            "lat": 352914618,
            "lon": -817416249,
            "elev": 272000
        }
    ]
}