{
    "name": "Angmering Raceway",
    "short_name": "AngmeringV2",
    "start_finish": {
        "lat": 508378974,
        "lon": -4708874,
        "elev": 36000
    },
    "pts": [
        {
            "lat": 508378974,
            "lon": -4708874,
            "elev": 36000
        },
        {
            "lat": 508378503,
            "lon": -4708856,
            "elev": 36000
        },
        {
            "lat": 508378027,
            "lon": -4708866,
            "elev": 36000
        },
        {
            "lat": 508377544,
            "lon": -4708890,
            "elev": 36000
        },
        {
            "lat": 508377057,
            "lon": -4708933,
            "elev": 36000
        },
        {
            "lat": 508376583,
            "lon": -4708987,
            "elev": 36000
        },
        {
            "lat": 508376122,
            "lon": -4709060,
            "elev": 36000
        },
        {
            "lat": 508375674,
            "lon": -4709135,
            "elev": 36000
        },
        {
            "lat": 508375225,
            "lon": -4709233,
            "elev": 36000
        },
        {
            "lat": 508374782,
            "lon": -4709372,
            "elev": 25000
        },
        {
            "lat": 508374267,
            "lon": -4709560,
            "elev": 25000
        },
        {
            "lat": 508373798,
            "lon": -4709750,
            "elev": 25000
        },
        {
            "lat": 508373364,
            "lon": -4709935,
            "elev": 25000
        },
        {
            "lat": 508372901,
            "lon": -4710191,
            "elev": 25000
        },
        {
            "lat": 508372514,
            "lon": -4710624,
            "elev": 25000
        },
        {
            "lat": 508372264,
            "lon": -4711307,
            "elev": 25000
        },
        {
            "lat": 508372338,
            "lon": -4711848,
            "elev": 25000
        },
        {
            "lat": 508372562,
            "lon": -4712214,
            "elev": 25000
        },
        {
            "lat": 508372925,
            "lon": -4712682,
            "elev": 25000
        },
        {
            "lat": 508373392,
            "lon": -4713039,
            "elev": 25000
        },
        {
            "lat": 508373824,
            "lon": -4713298,
            "elev": 25000
        },
        {
            "lat": 508374279,
            "lon": -4713531,
            "elev": 25000
        },
        {
            "lat": 508374757,
            "lon": -4713757,
            "elev": 25000
        },
        {
            "lat": 508375250,
            "lon": -4713969,
            "elev": 36000
        },
        {
            "lat": 508375752,
            "lon": -4714169,
            "elev": 36000
        },
        {
            "lat": 508376264,
            "lon": -4714367,
            "elev": 36000
        },
        {
            "lat": 508376785,
            "lon": -4714579,
            "elev": 36000
        },
        {
            "lat": 508377289,
            "lon": -4714755,
            "elev": 36000
        },
        {
            "lat": 508377779,
            "lon": -4714916,
            "elev": 36000
        },
        {
            "lat": 508378248,
            "lon": -4715057,
            "elev": 36000
        },
        {
            "lat": 508378773,
            "lon": -4715201,
            "elev": 36000
        },
        {
            "lat": 508379270,
            "lon": -4715328,
            "elev": 36000
        },
        {
            "lat": 508379734,
            "lon": -4715405,
            "elev": 36000
        },
        {
            "lat": 508380180,
            "lon": -4715296,
            "elev": 36000
        },
        {
            "lat": 508380632,
            "lon": -4714919,
            "elev": 36000
        },
        {
            "lat": 508380901,
            "lon": -4714307,
            "elev": 36000
        },
        {
            "lat": 508380838,
            "lon": -4713531,
            "elev": 36000
        },
        {
            "lat": 508380515,
            "lon": -4712997,
            "elev": 36000
        },
        {
            "lat": 508380133,
            "lon": -4712617,
            "elev": 36000
        },
        {
            "lat": 508379747,
            "lon": -4712221,
            "elev": 36000
        },
        {
            "lat": 508379352,
            "lon": -4711763,
            "elev": 36000
        },
        {
            "lat": 508379026,
            "lon": -4711203,
            "elev": 36000
        },
        {
            "lat": 508378891,
            "lon": -4710437,
            "elev": 36000
        },
        {
            "lat": 508379236,
            "lon": -4709949,
            "elev": 36000
        },
        {
            "lat": 508379679,
            "lon": -4710253,
            "elev": 36000
        },
        {
            "lat": 508380026,
            "lon": -4710707,
            "elev": 36000
        },
        {
            "lat": 508380425,
            "lon": -4711252,
            "elev": 36000
        },
        {
            "lat": 508380792,
            "lon": -4711792,
            "elev": 36000
        },
        {
            "lat": 508381110,
            "lon": -4712295,
            "elev": 36000
        },
        {
            "lat": 508381413,
            "lon": -4712856,
            "elev": 36000
        },
        {
            "lat": 508381663,
            "lon": -4713448,
            "elev": 36000
        },
        {
            "lat": 508381911,
            "lon": -4714163,
            "elev": 36000
        },
        {
            "lat": 508382148,
            "lon": -4714847,
            "elev": 36000
        },
        {
            "lat": 508382424,
            "lon": -4715436,
            "elev": 36000
        },
        {
            "lat": 508382843,
            "lon": -4715915,
            "elev": 36000
        },
        {
            "lat": 508383315,
            "lon": -4715951,
            "elev": 36000
        },
        {
            "lat": 508383737,
            "lon": -4715515,
            "elev": 36000
        },
        {
            "lat": 508383956,
            "lon": -4714879,
            "elev": 36000
        },
        {
            "lat": 508384139,
            "lon": -4714127,
            "elev": 36000
        },
        {
            "lat": 508384275,
            "lon": -4713441,
            "elev": 36000
        },
        {
            "lat": 508384346,
            "lon": -4712717,
            "elev": 36000
        },
        {
            "lat": 508384363,
            "lon": -4711986,
            "elev": 36000
        },
        {
            "lat": 508384286,
            "lon": -4711280,
            "elev": 36000
        },
        {
            "lat": 508384040,
            "lon": -4710581,
            "elev": 36000
        },
        {
            "lat": 508383687,
            "lon": -4710053,
            "elev": 36000
        },
        {
            "lat": 508383267,
            "lon": -4709774,
            "elev": 36000
        },
        {
            "lat": 508382771,
            "lon": -4709929,
            "elev": 36000
        },
        {
            "lat": 508382297,
            "lon": -4710266,
            "elev": 36000
        },
        {
            "lat": 508381812,
            "lon": -4710484,
            "elev": 36000
        },
        {
            "lat": 508381367,
            "lon": -4710342,
            "elev": 36000
        },
        {
            "lat": 508380906,
            "lon": -4709963,
            "elev": 36000
        },
        {
            "lat": 508380496,
            "lon": -4709588,
            "elev": 36000
        },
        {
            "lat": 508380033,
            "lon": -4709244,
            "elev": 36000
        },
        {
            "lat": 508379515,
            "lon": -4709005,
            "elev": 36000
        },
        {
            "lat": 508378974,
            "lon": -4708874,
            "elev": 36000
        }
    ]
}